Metadata-Version: 2.4
Name: iflow-mcp_kukapay_crypto-rss-mcp
Version: 0.1.0
Summary: Add your description here
License-File: LICENSE
Requires-Python: >=3.10
Requires-Dist: feedparser>=6.0.11
Requires-Dist: html2text>=2025.4.15
Requires-Dist: mcp[cli]>=1.6.0
Requires-Dist: opml>=0.5
